odoo/addons/purchase_vendor_bill_breakdown/README.rst
odoo/addons/purchase_vendor_bill_breakdown/__init__.py
odoo/addons/purchase_vendor_bill_breakdown/__manifest__.py
odoo/addons/purchase_vendor_bill_breakdown/data/demo.xml
odoo/addons/purchase_vendor_bill_breakdown/i18n/it.po
odoo/addons/purchase_vendor_bill_breakdown/i18n/purchase_vendor_bill_breakdown.pot
odoo/addons/purchase_vendor_bill_breakdown/models/__init__.py
odoo/addons/purchase_vendor_bill_breakdown/models/account_move.py
odoo/addons/purchase_vendor_bill_breakdown/models/product_supplierinfo.py
odoo/addons/purchase_vendor_bill_breakdown/models/product_supplierinfo_component.py
odoo/addons/purchase_vendor_bill_breakdown/models/purchase_order.py
odoo/addons/purchase_vendor_bill_breakdown/models/purchase_order_line.py
odoo/addons/purchase_vendor_bill_breakdown/models/purchase_order_line_component.py
odoo/addons/purchase_vendor_bill_breakdown/readme/CONTRIBUTORS.rst
odoo/addons/purchase_vendor_bill_breakdown/readme/DESCRIPTION.rst
odoo/addons/purchase_vendor_bill_breakdown/readme/USAGE.rst
odoo/addons/purchase_vendor_bill_breakdown/security/ir.model.access.csv
odoo/addons/purchase_vendor_bill_breakdown/static/description/icon.png
odoo/addons/purchase_vendor_bill_breakdown/static/description/index.html
odoo/addons/purchase_vendor_bill_breakdown/tests/__init__.py
odoo/addons/purchase_vendor_bill_breakdown/tests/common.py
odoo/addons/purchase_vendor_bill_breakdown/tests/test_account_move_create.py
odoo/addons/purchase_vendor_bill_breakdown/tests/test_components_flow.py
odoo/addons/purchase_vendor_bill_breakdown/tests/test_product_supplierinfo.py
odoo/addons/purchase_vendor_bill_breakdown/tests/test_product_supplierinfo_component.py
odoo/addons/purchase_vendor_bill_breakdown/tests/test_purchase_order.py
odoo/addons/purchase_vendor_bill_breakdown/tests/test_purchase_order_line.py
odoo/addons/purchase_vendor_bill_breakdown/views/product_supplierinfo_views.xml
odoo14_addon_purchase_vendor_bill_breakdown-14.0.1.0.1.dist-info/METADATA
odoo14_addon_purchase_vendor_bill_breakdown-14.0.1.0.1.dist-info/WHEEL
odoo14_addon_purchase_vendor_bill_breakdown-14.0.1.0.1.dist-info/top_level.txt
odoo14_addon_purchase_vendor_bill_breakdown-14.0.1.0.1.dist-info/RECORD
